{
   "server":[
      
    {
      "flag": "jp.png",
      "countryName": "Japan",
      "config": ""
    },
          {
      "flag": "de.png",
      "countryName": "Germany",
      "config": ""
    }
      ,
          {
      "flag": "ca.png",
      "countryName": "Canada",
      "config": ""
    },
              {
            "flag": "kr.png",
            "countryName": "Korea",
            "config": ""
        },
                  {
      "flag": "vn.png",
      "countryName": "Vietnam",
      "config": ""
    },
    {
      "flag": "ru.png",
      "countryName": "Russia",
      "config": ""
    },
       
            
              {
            "flag": "th.png",
            "countryName": "Thailand",
            "config": ""
        },
         
              {
            "flag": "kz.png",
            "countryName": "Kazakhstan",
            "config": ""
        },
                {
      "flag": "jp.png",
      "countryName": "Japan",
      "config": ""
    }
      
   ]
}
